pocket_joe/__init__.py
pocket_joe/core.py
pocket_joe/memory_runtime.py
pocket_joe/message.py
pocket_joe/policy_decorators.py
pocket_joe/policy_wrappers.py
pocket_joe-0.2.0.10.dist-info/METADATA
pocket_joe-0.2.0.10.dist-info/WHEEL
pocket_joe-0.2.0.10.dist-info/RECORD
