Metadata-Version: 2.4
Name: pocket-joe
Version: 0.2.0.10
Summary: A correct, simple, performant, and pythonic framework for building durable AI agents
Requires-Python: >=3.12
Requires-Dist: fastmcp>=2.13.2
Provides-Extra: examples
Requires-Dist: anthropic>=0.20.0; extra == 'examples'
Requires-Dist: beautifulsoup4>=4.11.0; extra == 'examples'
Requires-Dist: ddgs>=9.9.1; extra == 'examples'
Requires-Dist: google-genai>=1.55.0; extra == 'examples'
Requires-Dist: httpx>=0.27.0; extra == 'examples'
Requires-Dist: openai>=1.0.0; extra == 'examples'
Requires-Dist: pillow>=12.0.0; extra == 'examples'
Requires-Dist: python-dotenv>=1.2.1; extra == 'examples'
Requires-Dist: pyyaml>=6.0; extra == 'examples'
Requires-Dist: requests>=2.28.0; extra == 'examples'
Requires-Dist: youtube-transcript-api>=0.6.0; extra == 'examples'
